scenepic/__init__.py
scenepic/_scenepic.cp311-win_amd64.pyd
scenepic/audio_track.py
scenepic/audio_track.pyi
scenepic/camera.py
scenepic/camera.pyi
scenepic/canvas2d.py
scenepic/canvas2d.pyi
scenepic/canvas3d.py
scenepic/canvas3d.pyi
scenepic/drop_down_menu.py
scenepic/drop_down_menu.pyi
scenepic/focus_point.py
scenepic/focus_point.pyi
scenepic/frame2d.py
scenepic/frame2d.pyi
scenepic/frame3d.py
scenepic/frame3d.pyi
scenepic/globals.py
scenepic/globals.pyi
scenepic/graph.py
scenepic/graph.pyi
scenepic/image.py
scenepic/image.pyi
scenepic/label.py
scenepic/label.pyi
scenepic/layer_settings.py
scenepic/layer_settings.pyi
scenepic/loop_subdivision_stencil.py
scenepic/loop_subdivision_stencil.pyi
scenepic/mesh.py
scenepic/mesh.pyi
scenepic/mesh_info.py
scenepic/mesh_info.pyi
scenepic/scene.py
scenepic/scene.pyi
scenepic/scene_jupyter_template.js
scenepic/shading.py
scenepic/shading.pyi
scenepic/text_panel.py
scenepic/text_panel.pyi
scenepic/ui_parameters.py
scenepic/ui_parameters.pyi
scenepic/version.py
scenepic/video.py
scenepic/video.pyi
scenepic/video_writer.py
scenepic-1.1.2.dist-info/licenses/LICENSE
scenepic-1.1.2.dist-info/METADATA
scenepic-1.1.2.dist-info/WHEEL
scenepic-1.1.2.dist-info/top_level.txt
scenepic-1.1.2.dist-info/RECORD
