Metadata-Version: 2.1
Name: scenepic
Version: 1.1.2
Summary: 3D Visualization Made Easy
Home-page: https://microsoft.github.io/scenepic/
Author: ScenePic Team
Author-email: scenepic@microsoft.com
Project-URL: Documentation, https://microsoft.github.io/scenepic/
Project-URL: Bug Reports, https://github.com/microsoft/scenepic/issues
Project-URL: Source, https://github.com/microsoft/scenepic
Classifier: Development Status :: 5 - Production/Stable
Classifier: Programming Language :: Python :: 3
Classifier: Programming Language :: Python :: 3.8
Classifier: Programming Language :: Python :: 3.9
Classifier: Programming Language :: Python :: 3.10
Classifier: Programming Language :: Python :: 3.11
Classifier: Programming Language :: Python :: 3.12
Classifier: Programming Language :: Python :: 3.13
Classifier: Programming Language :: Python :: 3.14
Classifier: Programming Language :: Python :: 3 :: Only
Classifier: Intended Audience :: Science/Research
Classifier: Topic :: Scientific/Engineering :: Visualization
Classifier: License :: OSI Approved :: MIT License
Requires-Python: >=3.8, <4
License-File: LICENSE
Requires-Dist: numpy>=1.16.2
Requires-Dist: pillow>=5.2.0
Requires-Dist: scipy>=1.4.1
Provides-Extra: dev
Requires-Dist: azure-storage-blob>=12.0.0; extra == "dev"
Requires-Dist: azure-common; extra == "dev"
Requires-Dist: nbstripout; extra == "dev"
Requires-Dist: pytest-md; extra == "dev"
Requires-Dist: pytest-emoji; extra == "dev"
Requires-Dist: pytest-cov; extra == "dev"
Requires-Dist: pytest; extra == "dev"
Requires-Dist: requests; extra == "dev"
Requires-Dist: sphinx; extra == "dev"
Requires-Dist: sphinx-autodoc-typehints; extra == "dev"
Requires-Dist: sphinx-rtd-theme; extra == "dev"
Requires-Dist: twine; extra == "dev"
Requires-Dist: wheel; extra == "dev"
Provides-Extra: video
Requires-Dist: opencv-python; extra == "video"
